Metadata-Version: 2.0
Name: cocy
Version: 0.3
Summary: A components library for UPnP.
Home-page: http://packages.python.org/cocy
Author: Michael N. Lipp
Author-email: mnl@mnl.de
License: GPL
Keywords: circuits UPnP
Platform: UNKNOWN
Classifier: Development Status :: 3 - Alpha
Classifier: License :: OSI Approved :: GNU General Public License (GPL)
Requires-Dist: circuits (==3.2)
Requires-Dist: Tenjin
Requires-Dist: rbtranslations
Requires-Dist: circuits-bricks (==0.4.4)
